azure/mgmt/sql/__init__.py
azure/mgmt/sql/_configuration.py
azure/mgmt/sql/_sql_management_client.py
azure/mgmt/sql/_version.py
azure/mgmt/sql/aio/__init__.py
azure/mgmt/sql/aio/_configuration.py
azure/mgmt/sql/aio/_sql_management_client.py
azure/mgmt/sql/aio/operations/__init__.py
azure/mgmt/sql/aio/operations/_backup_short_term_retention_policies_operations.py
azure/mgmt/sql/aio/operations/_capabilities_operations.py
azure/mgmt/sql/aio/operations/_data_masking_policies_operations.py
azure/mgmt/sql/aio/operations/_data_masking_rules_operations.py
azure/mgmt/sql/aio/operations/_data_warehouse_user_activities_operations.py
azure/mgmt/sql/aio/operations/_database_advisors_operations.py
azure/mgmt/sql/aio/operations/_database_automatic_tuning_operations.py
azure/mgmt/sql/aio/operations/_database_blob_auditing_policies_operations.py
azure/mgmt/sql/aio/operations/_database_columns_operations.py
azure/mgmt/sql/aio/operations/_database_extensions_operations.py
azure/mgmt/sql/aio/operations/_database_operations_operations.py
azure/mgmt/sql/aio/operations/_database_recommended_actions_operations.py
azure/mgmt/sql/aio/operations/_database_schemas_operations.py
azure/mgmt/sql/aio/operations/_database_security_alert_policies_operations.py
azure/mgmt/sql/aio/operations/_database_tables_operations.py
azure/mgmt/sql/aio/operations/_database_usages_operations.py
azure/mgmt/sql/aio/operations/_database_vulnerability_assessment_rule_baselines_operations.py
azure/mgmt/sql/aio/operations/_database_vulnerability_assessment_scans_operations.py
azure/mgmt/sql/aio/operations/_database_vulnerability_assessments_operations.py
azure/mgmt/sql/aio/operations/_databases_operations.py
azure/mgmt/sql/aio/operations/_deleted_servers_operations.py
azure/mgmt/sql/aio/operations/_elastic_pool_activities_operations.py
azure/mgmt/sql/aio/operations/_elastic_pool_database_activities_operations.py
azure/mgmt/sql/aio/operations/_elastic_pool_operations_operations.py
azure_mgmt_sql-3.0.0.dist-info/METADATA
azure_mgmt_sql-3.0.0.dist-info/WHEEL
azure_mgmt_sql-3.0.0.dist-info/top_level.txt
azure_mgmt_sql-3.0.0.dist-info/RECORD
